{
  "url": "https://dcc-cde.ca.gov/",
  "requestedUrl": "https://dcc-cde.ca.gov/",
  "timestamp": 1708176198088,
  "ranks": {
    "hundos": 50,
    "performance": 129,
    "accessibility": 12,
    "cumulative": 49
  },
  "lighthouse": {
    "version": "11.5.0",
    "performance": 0.61,
    "accessibility": 1,
    "bestPractices": 0.96,
    "seo": 0.97,
    "total": 354
  },
  "firstContentfulPaint": 3954.7737500000003,
  "firstMeaningfulPaint": 3954.7737500000003,
  "speedIndex": 6533.414617755518,
  "largestContentfulPaint": 14582.3755,
  "totalBlockingTime": 9,
  "cumulativeLayoutShift": 0.05495921787990569,
  "timeToInteractive": 7028.903249999999,
  "maxPotentialFirstInputDelay": 65,
  "timeToFirstByte": 552.386,
  "weight": {
    "summary": "48 requests • 2.0 MiB",
    "total": 2092231,
    "image": 1421652,
    "imageCount": 14,
    "script": 610781,
    "scriptCount": 19,
    "document": 10498,
    "font": 0,
    "fontCount": 0,
    "stylesheet": 47194,
    "stylesheetCount": 9,
    "thirdParty": 624735,
    "thirdPartyCount": 6
  },
  "run": {
    "number": 1,
    "total": 1
  },
  "sidequests": {
    "-weight.total": 154,
    "+weight.total": 269,
    "-weight.document": 40,
    "+weight.document": 379,
    "-weight.script": 137,
    "+weight.script": 283,
    "-weight.image": 248,
    "+weight.image": 169,
    "-weight.font": 1,
    "+weight.font": 351,
    "+weight.fontCount": 25,
    "-timeToFirstByte": 344,
    "-totalBlockingTime": 17,
    "-largestContentfulPaint": 264
  },
  "axe": {
    "passes": 485,
    "violations": 0
  }
}