{
  "url": "https://www.calbar.ca.gov/",
  "requestedUrl": "https://www.calbar.ca.gov/",
  "timestamp": 1707434030457,
  "ranks": {
    "hundos": 220,
    "performance": 156,
    "accessibility": 242,
    "cumulative": 220
  },
  "lighthouse": {
    "version": "11.5.0",
    "performance": 0.41,
    "accessibility": 0.82,
    "bestPractices": 0.56,
    "seo": 0.98,
    "total": 277
  },
  "firstContentfulPaint": 3393.70885,
  "firstMeaningfulPaint": 4147.25642,
  "speedIndex": 5035.7713091014975,
  "largestContentfulPaint": 8410.70736,
  "totalBlockingTime": 294.49999999999955,
  "cumulativeLayoutShift": 0.3793355377718074,
  "timeToInteractive": 7257.154459999999,
  "maxPotentialFirstInputDelay": 553.9999999999991,
  "timeToFirstByte": 49.664999999999964,
  "weight": {
    "summary": "51 requests • 1.1 MiB",
    "total": 1140444,
    "image": 681187,
    "imageCount": 14,
    "script": 330393,
    "scriptCount": 18,
    "document": 28211,
    "font": 64127,
    "fontCount": 6,
    "stylesheet": 30218,
    "stylesheetCount": 7,
    "thirdParty": 286424,
    "thirdPartyCount": 6
  },
  "run": {
    "number": 1,
    "total": 1
  },
  "sidequests": {
    "-weight.total": 48,
    "+weight.total": 212,
    "-weight.document": 85,
    "+weight.document": 175,
    "-weight.script": 40,
    "+weight.script": 218,
    "-weight.image": 116,
    "+weight.image": 142,
    "-weight.font": 21,
    "+weight.font": 199,
    "+weight.fontCount": 14,
    "-timeToFirstByte": 98,
    "-totalBlockingTime": 133,
    "-largestContentfulPaint": 109
  },
  "axe": {
    "passes": 510,
    "violations": 22
  }
}