{
  "url": "https://bcdc.ca.gov/",
  "requestedUrl": "https://bcdc.ca.gov/",
  "timestamp": 1707761945442,
  "ranks": {
    "hundos": 312,
    "performance": 235,
    "accessibility": 5,
    "cumulative": 312
  },
  "lighthouse": {
    "version": "11.5.0",
    "performance": 0.49,
    "accessibility": 1,
    "bestPractices": 0.52,
    "seo": 0.9,
    "total": 291
  },
  "firstContentfulPaint": 2232.504,
  "firstMeaningfulPaint": 4064.2369999999983,
  "speedIndex": 5364.98696171212,
  "largestContentfulPaint": 10579.458999999995,
  "totalBlockingTime": 40,
  "cumulativeLayoutShift": 0.42018857639346924,
  "timeToInteractive": 8995.028999999999,
  "maxPotentialFirstInputDelay": 84,
  "timeToFirstByte": 115.37400000000001,
  "weight": {
    "summary": "76 requests • 8.8 MiB",
    "total": 9183290,
    "image": 1551784,
    "imageCount": 19,
    "script": 864281,
    "scriptCount": 17,
    "document": 19312,
    "font": 166806,
    "fontCount": 5,
    "stylesheet": 106451,
    "stylesheetCount": 9,
    "thirdParty": 7397941,
    "thirdPartyCount": 9
  },
  "run": {
    "number": 1,
    "total": 1
  },
  "sidequests": {
    "-weight.total": 377,
    "+weight.total": 49,
    "-weight.document": 93,
    "+weight.document": 330,
    "-weight.script": 191,
    "+weight.script": 231,
    "-weight.image": 260,
    "+weight.image": 162,
    "-weight.font": 178,
    "+weight.font": 181,
    "+weight.fontCount": 19,
    "-timeToFirstByte": 220,
    "-totalBlockingTime": 64,
    "-largestContentfulPaint": 204
  },
  "axe": {
    "passes": 954,
    "violations": 0
  }
}