{
  "url": "https://www.sos.ca.gov/elections/",
  "requestedUrl": "https://vote.ca.gov/",
  "timestamp": 1707793673602,
  "ranks": {
    "hundos": 62,
    "performance": 33,
    "accessibility": 27,
    "cumulative": 62
  },
  "lighthouse": {
    "version": "11.5.0",
    "performance": 0.86,
    "accessibility": 1,
    "bestPractices": 0.74,
    "seo": 0.91,
    "total": 351
  },
  "firstContentfulPaint": 2075.991,
  "firstMeaningfulPaint": 2075.991,
  "speedIndex": 3498.3348751328213,
  "largestContentfulPaint": 3823.2470000000003,
  "totalBlockingTime": 35.5,
  "cumulativeLayoutShift": 0.0005067018885875927,
  "timeToInteractive": 8234.335,
  "maxPotentialFirstInputDelay": 66,
  "timeToFirstByte": 37.831,
  "weight": {
    "summary": "45 requests • 1.2 MiB",
    "total": 1296789,
    "image": 188956,
    "imageCount": 19,
    "script": 945574,
    "scriptCount": 13,
    "document": 15633,
    "font": 77371,
    "fontCount": 1,
    "stylesheet": 67920,
    "stylesheetCount": 8,
    "thirdParty": 322838,
    "thirdPartyCount": 3
  },
  "run": {
    "number": 1,
    "total": 1
  },
  "sidequests": {
    "-weight.total": 78,
    "+weight.total": 348,
    "-weight.document": 72,
    "+weight.document": 351,
    "-weight.script": 232,
    "+weight.script": 190,
    "-weight.image": 53,
    "+weight.image": 369,
    "-weight.font": 58,
    "+weight.font": 301,
    "+weight.fontCount": 23,
    "-timeToFirstByte": 118,
    "-totalBlockingTime": 59,
    "-largestContentfulPaint": 41
  },
  "axe": {
    "passes": 1128,
    "violations": 1
  }
}